LICENSE
MANIFEST.in
README.md
requirements.txt
setup.cfg
setup.py
bluemist/__init__.py
bluemist/environment.py
bluemist/logging.config
bluemist/main.py
bluemist/mainPipelineTest.py
bluemist/artifacts/api/predict.py
bluemist/artifacts/api/__pycache__/predict.cpython-39.pyc
bluemist/artifacts/eda/autoviz/target/cat_var_plots.html
bluemist/artifacts/eda/autoviz/target/distplots_cats.html
bluemist/artifacts/eda/autoviz/target/distplots_nums.html
bluemist/artifacts/eda/autoviz/target/heatmaps.html
bluemist/artifacts/eda/autoviz/target/kde_plots.html
bluemist/artifacts/eda/autoviz/target/pair_scatters.html
bluemist/artifacts/eda/autoviz/target/scatterplots.html
bluemist/artifacts/eda/autoviz/target/violinplots.html
bluemist/artifacts/logs/bluemist.log
bluemist/artifacts/logs/bluemist.log.1
bluemist/artifacts/logs/bluemist.log.10
bluemist/artifacts/logs/bluemist.log.11
bluemist/artifacts/logs/bluemist.log.12
bluemist/artifacts/logs/bluemist.log.13
bluemist/artifacts/logs/bluemist.log.14
bluemist/artifacts/logs/bluemist.log.15
bluemist/artifacts/logs/bluemist.log.16
bluemist/artifacts/logs/bluemist.log.17
bluemist/artifacts/logs/bluemist.log.18
bluemist/artifacts/logs/bluemist.log.19
bluemist/artifacts/logs/bluemist.log.2
bluemist/artifacts/logs/bluemist.log.20
bluemist/artifacts/logs/bluemist.log.3
bluemist/artifacts/logs/bluemist.log.4
bluemist/artifacts/logs/bluemist.log.5
bluemist/artifacts/logs/bluemist.log.6
bluemist/artifacts/logs/bluemist.log.7
bluemist/artifacts/logs/bluemist.log.8
bluemist/artifacts/logs/bluemist.log.9
bluemist/classification/__init__.py
bluemist/datasets/auto-mpg/Index
bluemist/datasets/auto-mpg/auto-mpg.csv
bluemist/datasets/auto-mpg/auto-mpg.data
bluemist/datasets/auto-mpg/auto-mpg.data-original
bluemist/datasets/auto-mpg/auto-mpg.names
bluemist/datasource/__init__.py
bluemist/datasource/aws.py
bluemist/datasource/azure.py
bluemist/datasource/database.py
bluemist/datasource/file.py
bluemist/datasource/gcp.py
bluemist/eda/__init__.py
bluemist_ai.egg-info/PKG-INFO
bluemist_ai.egg-info/SOURCES.txt
bluemist_ai.egg-info/dependency_links.txt
bluemist_ai.egg-info/requires.txt
bluemist_ai.egg-info/top_level.txt