Metadata-Version: 2.1
Name: bluemist-ai
Version: 0.1.1.17
Summary: My package description
Home-page: https://github.com/shashanka89/bluemist-ai
Author: Shashank Agrawal
Author-email: shashanka89@gmail.com
License: MIT
Requires-Python: >=3.9
License-File: LICENSE
